{
  "status": "OK",
  "data": [
    {
      "id": 1,
      "date": "2024-06-25",
      "title": "취업 준비 특강 공지",
      "userName": "manager",
      "content": "안녕하세요 수강생 여러분! <br/>금일 18시에서 20시까지 취업 준비 특강 진행 예정입니다~ <br/>모두 참여하셔서 여러분의 프론트엔드 개발자 취업 준비에 도움이 되었으면 좋겠습니다."
    },
    {
      "id": "2",
      "date": "2024-06-25",
      "title": "(화) 퇴실 공지",
      "userName": "manager",
      "content": "화요일이 지나가고 있습니다! 취업특강으로 원하시는 정보를 얻으셨길 바라겠습니다!!<br/>오늘도 너무너무 고생 많으셨습니다~!<br/>공지사항이 많으니 하나씩 꼼꼼히 확인 부탁드리겠습니다."
    },
    {
      "id": "3",
      "date": "2024-06-26",
      "title": "(수) 입실 공지",
      "userName": "manager",
      "content": "수요일 아침이 밝았습니다!!! 작일 취업특강으로 원하시는 정보를 얻으셨을까요??<br/>오늘도 빠이팅입니다~ 좋은 하루 되길 바라겠습니다!<br/>:전구:공지사항이 많으니 하나씩 꼼꼼히 확인 부탁드리겠습니다.:전구:"
    }
  ]
}
